VirtualKey/__init__.py
VirtualKey/ctypes_key.py
VirtualKey/ctypes_key_creator.py
VirtualKey/example.py
VirtualKey/key_strategy.py
VirtualKey/new_down_up.py
VirtualKey-0.0.5.dist-info/LICENSE.txt
VirtualKey-0.0.5.dist-info/METADATA
VirtualKey-0.0.5.dist-info/WHEEL
VirtualKey-0.0.5.dist-info/top_level.txt
VirtualKey-0.0.5.dist-info/RECORD
