Metadata-Version: 2.1
Name: VirtualKey
Version: 0.0.5
Summary: VirtualKey with ctypes. 更新避免lol的屏蔽
Home-page: https://github.com/bode135/VirtualKey_with_Ctypes
Author: bode135
Author-email: 2248270222@qq.com
License: UNKNOWN
Platform: UNKNOWN
Classifier: Programming Language :: Python :: 3
Classifier: License :: OSI Approved :: MIT License
Classifier: Operating System :: OS Independent
Requires-Python: >=3.6
Requires-Dist: pywin32
Requires-Dist: bdtime
Requires-Dist: keyboard
